purelyjs-0.1.4.dist-info/WHEEL
purelyjs-0.1.4.dist-info/pydist.json
purelyjs-0.1.4.dist-info/RECORD
purelyjs-0.1.4.dist-info/DESCRIPTION.rst
purelyjs-0.1.4.dist-info/METADATA
purelyjs-0.1.4.dist-info/top_level.txt
purelyjs-0.1.4.dist-info/entry_points.txt
purelyjs/testmodule.py
purelyjs/io.py
purelyjs/config.py
purelyjs/__init__.py
purelyjs/testrunner.py
purelyjs/interpreter.py
purelyjs/main.py
purelyjs/js/purely.js
purelyjs-0.1.4.data/scripts/purelyjs
